rotograd/__init__.py
rotograd/rotograd.py
rotograd-0.1.6.0.dist-info/LICENSE.md
rotograd-0.1.6.0.dist-info/METADATA
rotograd-0.1.6.0.dist-info/WHEEL
rotograd-0.1.6.0.dist-info/top_level.txt
rotograd-0.1.6.0.dist-info/RECORD
