Metadata-Version: 2.1
Name: rotograd
Version: 0.1.6.0
Summary: RotoGrad: Gradient Homogenization in Multitask Learning in Pytorch
Home-page: https://github.com/adrianjav/rotograd
Author: Adrián Javaloy
Author-email: adrian.javaloy@gmail.com
License: MIT
Keywords: Multitask Learning,Gradient Alignment,Gradient Interference,Negative Transfer,Pytorch,Positive Transfer,Gradient Conflict
Classifier: Development Status :: 3 - Alpha
Classifier: Programming Language :: Python
Classifier: Programming Language :: Python :: 3
Classifier: Programming Language :: Python :: 3.7
Classifier: License :: OSI Approved :: MIT License
Classifier: Topic :: Scientific/Engineering
Classifier: Topic :: Scientific/Engineering :: Artificial Intelligence
Classifier: Intended Audience :: Science/Research
Classifier: Intended Audience :: Developers
Classifier: Operating System :: OS Independent
Requires-Python: >=3.7
License-File: LICENSE.md
Requires-Dist: torch (>=1.5)
Requires-Dist: geotorch
Provides-Extra: docs
Requires-Dist: sphinx ; extra == 'docs'
Requires-Dist: sphinx-autodoc-typehints ; extra == 'docs'
Requires-Dist: sphinx-rtd-theme ; extra == 'docs'
